<?xml version="1.0" encoding="UTF-8"?>

<beans xmlns="http://www.springframework.org/schema/beans"
	   xmlns:xsi="http://www.w3.org/2001/XMLSchema-instance" 
	   xmlns:context="http://www.springframework.org/schema/context"
	   xmlns:util="http://www.springframework.org/schema/util"
	   xsi:schemaLocation="http://www.springframework.org/schema/beans 
           http://www.springframework.org/schema/beans/spring-beans-2.5.xsd
           http://www.springframework.org/schema/context
           http://www.springframework.org/schema/context/spring-context-2.5.xsd
           http://www.springframework.org/schema/util
           http://www.springframework.org/schema/util/spring-util-2.0.xsd">

	<context:component-scan base-package="org.openmrs.module.messaging" />

	<bean id="messagingMapping" class="org.springframework.web.servlet.handler.SimpleUrlHandlerMapping">
		<property name="order"><value>2</value></property>
		<property name="mappings">
			<props>
				<prop key="**/messagesPatientDashboardTab.portlet">messagesPatientDashboardTab</prop>
				<prop key="module/messaging/inbox.form">inboxController</prop>
				<prop key="module/messaging/compose_message.form">composeMessageController</prop>
				<prop key="module/messaging/sent_messages.form">sentMessagesController</prop>
				<prop key="module/messaging/external_conversations.form">externalConversationsController</prop>
				<prop key="module/messaging/settings.form">settingsController</prop>
				<prop key="module/messaging/manage_gatways.form">manageGatewaysController</prop>
			</props>
		</property>
	</bean>
		
	<bean id="inboxController" class="org.openmrs.module.messaging.web.controller.InboxController" />
	<bean id="composeMessageController" class="org.openmrs.module.messaging.web.controller.ComposeMessageController" />
	<bean id="sentMessagesController" class="org.openmrs.module.messaging.web.controller.SentMessagesController" />
	<bean id="externalConversationsController" class="org.openmrs.module.messaging.web.controller.ExternalConversationsController" />
	<bean id="settingsController" class="org.openmrs.module.messaging.web.controller.SettingsController" />
	
	<bean id="manageGatewaysController" class="org.openmrs.module.messaging.web.controller.ManageGatewaysController" >
		<property name="gatewayManager"><ref bean="gatewayManager"/></property>
	</bean>
	<bean id="messagesPatientDashboardTab" class="org.openmrs.module.messaging.web.controller.MessagingDashboardTabController" />

</beans>